{
  "logo": {
    "src": "https://www.andys.md/app/img/logo.svg",
    "alt": "logo",
    "href": ""
  },
  "menu": [
    {
      "id": 1,
      "title": "contactsList",
      "data": [
        {
          "id": 1,
          "city": "Chisinau",
          "telefone": "022 210-210",
          "href": ""
        },
        {
          "id": 2,
          "city": "Balti",
          "telefone": "023 120-210",
          "href": ""
        },
        {
          "id": 3,
          "city": "Cahul",
          "telefone": "078 84-84-84",
          "href": ""
        },
        {
          "id": 4,
          "city": "Comrat",
          "telefone": "078 22-00-88",
          "href": ""
        },
        {
          "id": 5,
          "city": "Ceadar-Lunga",
          "telefone": "079 22-44-66",
          "href": ""
        }
      ]
    },
    {
      "id": 2,
      "title": "partnerImages",
      "data": [
        {
          "id": 1,
          "src": "https://www.andys.md/app/img/brands/LaPlacinte.svg",
          "alt": "LaPlacinte",
          "href": "https://laplacinte.md/"
        },
        {
          "id": 2,
          "src": "https://www.andys.md/app/img/brands/CiaoCacao.svg",
          "alt": "CiaoCacao",
          "href": "https://ciaocacao.md/"
        },
        {
          "id": 3,
          "src": "https://www.andys.md/app/img/brands/Gustland.png",
          "alt": "Gustland",
          "href": "https://gustland.md/"
        }
      ]
    },
    {
      "id": 3,
      "title": "navList",
      "data": [
        {
          "id": 1,
          "title": "Menu",
          "href": "products",
          "subMenu": [
            {
              "id": 1,
              "title": "Pizza"
            },
            {
              "id": 2,
              "title": "Snacks"
            },
            {
              "id": 3,
              "title": "Salads"
            },
            {
              "id": 4,
              "title": "Soups"
            },
            {
              "id": 5,
              "title": "Main Dishes"
            },
            {
              "id": 6,
              "title": "Box"
            },
            {
              "id": 7,
              "title": "Breakfast"
            },
            {
              "id": 8,
              "title": "Cake"
            },
            {
              "id": 9,
              "title": "Dessert"
            },
            {
              "id": 10,
              "title": "Supplements"
            },
            {
              "id": 11,
              "title": "Beverages"
            },
            {
              "id": 12,
              "title": "Alcohol"
            }
          ]
        },
        {
          "id": 2,
          "title": "Restaurants",
          "href": "restaurants"
        },
        {
          "id": 3,
          "title": "News",
          "href": "news"
        }
      ]
    }
  ],
  "topSlider": [
    {
      "id": 1,
      "src": "https://www.andys.md/public/sliders/thumbs/version_2560x916x1/99e4fed4f4c30baa2e5787cd067edd4a.jpg",
      "alt": "Slide1",
      "href": "products/1"
    },
    {
      "id": 2,
      "src": "https://www.andys.md/public/sliders/thumbs/version_2560x916x1/4e9cd7974d39d3aea82fc6b69f45f718.jpg",
      "alt": "Slide2",
      "href": "products/2"
    },
    {
      "id": 3,
      "src": "https://www.andys.md/public/sliders/thumbs/version_2560x916x1/026bc0617f666d477ae65122d379f939.jpg",
      "alt": "Slide3",
      "href": "products/3"
    }
  ],
  "products": [
    {
      "id": 1,
      "title": "Pizza",
      "data": [
        {
          "id": 1,
          "src": "https://www.andys.md/public/menu/thumbs/version_712x785x1/c16804bcd0d47fce6c6d033b694a09fe.jpg",
          "title": "Rancho",
          "price": 105,
          "currency": "mdl"
        },
        {
          "id": 2,
          "src": "https://www.andys.md/public/menu/thumbs/version_712x785x1/9edc060af068da34bc5c8298755f11a2.jpg",
          "title": "Neapolitana",
          "price": 105,
          "currency": "mdl"
        },
        {
          "id": 3,
          "src": "https://www.andys.md/public/menu/thumbs/version_712x785x1/abe848cde189206049cae70fee65b2ad.jpg",
          "title": "Greek",
          "price": 110,
          "currency": "mdl"
        },
        {
          "id": 4,
          "src": "https://www.andys.md/public/menu/thumbs/version_712x785x1/1d9d15e01830693aa9d0e6b5851dd8d6.jpg",
          "title": "Mario",
          "price": 105,
          "currency": "mdl"
        },
        {
          "id": 5,
          "src": "https://www.andys.md/public/menu/thumbs/version_712x785x1/3a9c24985cb363b8cc326e00e39cad6e.jpg",
          "title": "Pepperoni",
          "price": 105,
          "currency": "mdl"
        }
      ]
    },
    {
      "id": 2,
      "title": "Snacks",
      "data": [
        {
          "id": 1,
          "src": "https://www.andys.md/public/menu/thumbs/version_712x785x1/6b5aef803cebc8365c8ec52419f7077f.jpg",
          "title": "Chicken sandwich",
          "price": 85,
          "currency": "mdl"
        },
        {
          "id": 2,
          "src": "https://www.andys.md/public/menu/thumbs/version_712x785x1/6ae82a8be7177e363d95ad893bdf6397.jpg",
          "title": "Potato surprise with cheese",
          "price": 65,
          "currency": "mdl"
        },
        {
          "id": 3,
          "src": "https://www.andys.md/public/menu/thumbs/version_712x785x1/b951e9ec4bfe24695dcc5cb5ba0e5128.jpg",
          "title": "Potato surprise with meat",
          "price": 70,
          "currency": "mdl"
        },
        {
          "id": 4,
          "src": "https://www.andys.md/public/menu/thumbs/version_712x785x1/0ad5cad10cc2f8721facb5d55549d719.jpg",
          "title": "Pepper Bruschetta",
          "price": 105,
          "currency": "mdl"
        },
        {
          "id": 5,
          "src": "https://www.andys.md/public/menu/thumbs/version_712x785x1/900a3ad96677eee49326d0830673356d.jpg",
          "title": "Salmon Bruschetta",
          "price": 135,
          "currency": "mdl"
        }
      ]
    },
    {
      "id": 3,
      "title": "Salads",
      "data": [
        {
          "id": 1,
          "src": "https://www.andys.md/public/menu/thumbs/version_712x785x1/b11f6824a28ef9a4bbce819d0c7b1318.jpg",
          "title": "Salmon salad",
          "price": 105,
          "currency": "mdl"
        },
        {
          "id": 2,
          "src": "https://www.andys.md/public/menu/thumbs/version_712x785x1/1d719651a8410e475ac9c4967492f9b8.jpg",
          "title": "Greek salad",
          "price": 70,
          "currency": "mdl"
        },
        {
          "id": 3,
          "src": "https://www.andys.md/public/menu/thumbs/version_712x785x1/1cf5154a846879c8bea17787be5ddada.jpg",
          "title": "Chicken salad",
          "price": 85,
          "currency": "mdl"
        },
        {
          "id": 4,
          "src": "https://www.andys.md/public/menu/thumbs/version_712x785x1/2804b560a76a90fa37502368328884bb.jpg",
          "title": "Beef salad",
          "price": 110,
          "currency": "mdl"
        },
        {
          "id": 5,
          "src": "https://www.andys.md/public/menu/thumbs/version_712x785x1/2d85e909ec5d562a009880ab4e90bd8c.jpg",
          "title": "Shrimp Caesar",
          "price": 105,
          "currency": "mdl"
        }
      ]
    }
  ],
  "footer": [
    {
      "id": 1,
      "title": "Company",
      "list": [
        {
          "id": 1,
          "name": "Career",
          "href": " "
        },
        {
          "id": 2,
          "name": "Feedback",
          "href": " "
        },
        {
          "id": 3,
          "name": "Contacts",
          "href": " "
        }
      ]
    },
    {
      "id": 2,
      "title": "Services",
      "list": [
        {
          "id": 1,
          "name": "Client card",
          "href": " "
        },
        {
          "id": 2,
          "name": "Corporate clients",
          "href": " "
        },
        {
          "id": 3,
          "name": "Kids parties",
          "href": " "
        },
        {
          "id": 4,
          "name": "Banquets",
          "href": " "
        }
      ]
    },
    {
      "id": 3,
      "title": "Delivery",
      "list": [
        {
          "id": 1,
          "name": "Chisinau",
          "href": " "
        },
        {
          "id": 2,
          "name": "Balti",
          "href": " "
        },
        {
          "id": 3,
          "name": "Cahul",
          "href": " "
        },
        {
          "id": 4,
          "name": "Comrat",
          "href": " "
        },
        {
          "id": 5,
          "name": "Ceadar-Lunga",
          "href": " "
        }
      ]
    }
  ],
  "clients": [
    {
      "email": "a@b",
      "password": "123",
      "id": 1
    },
    {
      "email": "a@c",
      "password": "123",
      "id": 2
    }
  ]
}